arcane_viewer/__init__.py
arcane_viewer/main.py
arcane_viewer/arcane/__init__.py
arcane_viewer/arcane/client.py
arcane_viewer/arcane/constants.py
arcane_viewer/arcane/exceptions.py
arcane_viewer/arcane/protocol.py
arcane_viewer/arcane/screen.py
arcane_viewer/arcane/session.py
arcane_viewer/arcane/threads/__init__.py
arcane_viewer/arcane/threads/client_base.py
arcane_viewer/arcane/threads/connect.py
arcane_viewer/arcane/threads/events.py
arcane_viewer/arcane/threads/v_desktop.py
arcane_viewer/assets/__init__.py
arcane_viewer/assets/app_icon.png
arcane_viewer/ui/__init__.py
arcane_viewer/ui/utilities.py
arcane_viewer/ui/custom_widgets/__init__.py
arcane_viewer/ui/custom_widgets/tangeant_universe.py
arcane_viewer/ui/dialogs/__init__.py
arcane_viewer/ui/dialogs/about.py
arcane_viewer/ui/dialogs/connecting.py
arcane_viewer/ui/dialogs/options.py
arcane_viewer/ui/dialogs/screen_selection.py
arcane_viewer/ui/dialogs/server_certificate.py
arcane_viewer/ui/dialogs/options_dialogs/__init__.py
arcane_viewer/ui/dialogs/options_dialogs/server_certificate_add_or_edit.py
arcane_viewer/ui/forms/__init__.py
arcane_viewer/ui/forms/connect.py
arcane_viewer/ui/forms/desktop.py
arcane_viewer-1.0.7.dist-info/LICENSE
arcane_viewer-1.0.7.dist-info/METADATA
arcane_viewer-1.0.7.dist-info/WHEEL
arcane_viewer-1.0.7.dist-info/entry_points.txt
arcane_viewer-1.0.7.dist-info/top_level.txt
arcane_viewer-1.0.7.dist-info/RECORD
